aleksis/apps/lesrooster/__init__.py
aleksis/apps/lesrooster/apps.py
aleksis/apps/lesrooster/frontend/components/CSVAdditionalParams.vue
aleksis/apps/lesrooster/frontend/components/additionalParams.graphql
aleksis/apps/lesrooster/frontend/components/breaks_and_slots/Break.vue
aleksis/apps/lesrooster/frontend/components/breaks_and_slots/LesroosterSlot.vue
aleksis/apps/lesrooster/frontend/components/breaks_and_slots/break.graphql
aleksis/apps/lesrooster/frontend/components/breaks_and_slots/slot.graphql
aleksis/apps/lesrooster/frontend/components/common/ColoredShortNameChip.vue
aleksis/apps/lesrooster/frontend/components/helper.graphql
aleksis/apps/lesrooster/frontend/components/lesson_raster/LessonRaster.vue
aleksis/apps/lesrooster/frontend/components/lesson_raster/SlotCard.vue
aleksis/apps/lesrooster/frontend/components/lesson_raster/SlotCreator.vue
aleksis/apps/lesrooster/frontend/components/supervision/Supervision.vue
aleksis/apps/lesrooster/frontend/components/supervision/supervision.graphql
aleksis/apps/lesrooster/frontend/components/timebound_course_config/TimeboundCourseConfigCRUDTable.vue
aleksis/apps/lesrooster/frontend/components/timebound_course_config/TimeboundCourseConfigRaster.vue
aleksis/apps/lesrooster/frontend/components/timebound_course_config/TimeboundCourseConfigRasterCell.vue
aleksis/apps/lesrooster/frontend/components/timebound_course_config/timeboundCourseConfig.graphql
aleksis/apps/lesrooster/frontend/components/timetable_management/BlockingCard.vue
aleksis/apps/lesrooster/frontend/components/timetable_management/BundleCard.vue
aleksis/apps/lesrooster/frontend/components/timetable_management/LessonCard.vue
aleksis/apps/lesrooster/frontend/components/timetable_management/LessonRatioChip.vue
aleksis/apps/lesrooster/frontend/components/timetable_management/PeriodCard.vue
aleksis/apps/lesrooster/frontend/components/timetable_management/TimetableManagement.vue
aleksis/apps/lesrooster/frontend/components/timetable_management/TimetableOverlayCard.vue
aleksis_app_lesrooster-1.0.1.dist-info/LICENCE.rst
aleksis_app_lesrooster-1.0.1.dist-info/METADATA
aleksis_app_lesrooster-1.0.1.dist-info/WHEEL
aleksis_app_lesrooster-1.0.1.dist-info/entry_points.txt
aleksis_app_lesrooster-1.0.1.dist-info/RECORD
