Metadata-Version: 2.3
Name: AlekSIS-App-Lesrooster
Version: 1.0.1
Summary: AlekSIS (School Information System) — App Lesrooster (Timetable Management Using Time Grids)
License: EUPL-1.2-or-later
Author: Julian Leucker
Author-email: julian.leucker@teckids.org
Maintainer: Jonathan Weth
Maintainer-email: jonathan.weth@teckids.org
Requires-Python: >=3.10,<4.0
Classifier: Environment :: Web Environment
Classifier: Intended Audience :: Education
Classifier: License :: Other/Proprietary License
Classifier: Programming Language :: Python :: 3
Classifier: Programming Language :: Python :: 3.10
Classifier: Programming Language :: Python :: 3.11
Classifier: Programming Language :: Python :: 3.12
Classifier: Programming Language :: Python :: 3.13
Classifier: Topic :: Education
Requires-Dist: AlekSIS-App-Chronos (>=4.0.0,<5.0.0)
Requires-Dist: AlekSIS-Core (>=4.0.0,<5.0.0)
Requires-Dist: django-recurrence (>=1.11.1,<2.0.0)
Project-URL: Documentation, https://aleksis.org/official/AlekSIS/docs/html/
Project-URL: Homepage, https://aleksis.org
Project-URL: Repository, https://edugit.org/AlekSIS/onboarding/AlekSIS-App-Lesrooster
